gauto/__init__.py
gauto/manager.py
gauto/Minitouch/Minitouch.py
gauto/Minitouch/__init__.py
gauto/common/__init__.py
gauto/common/adb_process.py
gauto/common/coordinate_transfer.py
gauto/common/platform_helper.py
gauto/common/protocol.py
gauto/common/rpc_thread.py
gauto/common/socket_client.py
gauto/common/utils.py
gauto/common/wetest_exceptions.py
gauto/common/wrapper.py
gauto/httptools/__init__.py
gauto/httptools/command.py
gauto/httptools/errorhandler.py
gauto/httptools/exceptions.py
gauto/httptools/remote_connection.py
gauto/httptools/utils.py
gauto/libs/__init__.py
gauto/libs/imap_utf7.py
gauto/libs/six.py
gauto/libs/uiauto/__init__.py
gauto/libs/uiauto/uiautomator.py
gauto/libs/urllib3/__init__.py
gauto/libs/urllib3/_collections.py
gauto/libs/urllib3/connection.py
gauto/libs/urllib3/connectionpool.py
gauto/libs/urllib3/exceptions.py
gauto/libs/urllib3/fields.py
gauto/libs/urllib3/filepost.py
gauto/libs/urllib3/poolmanager.py
gauto/libs/urllib3/request.py
gauto/libs/urllib3/response.py
gauto/libs/urllib3/contrib/__init__.py
gauto/libs/urllib3/contrib/appengine.py
gauto/libs/urllib3/contrib/ntlmpool.py
gauto/libs/urllib3/contrib/pyopenssl.py
gauto/libs/urllib3/contrib/socks.py
gauto/libs/urllib3/packages/__init__.py
gauto/libs/urllib3/packages/ordered_dict.py
gauto/libs/urllib3/packages/six.py
gauto/libs/urllib3/packages/backports/__init__.py
gauto/libs/urllib3/packages/backports/makefile.py
gauto/libs/urllib3/packages/ssl_match_hostname/__init__.py
gauto/libs/urllib3/packages/ssl_match_hostname/_implementation.py
gauto/libs/urllib3/util/__init__.py
gauto/libs/urllib3/util/connection.py
gauto/libs/urllib3/util/request.py
gauto/libs/urllib3/util/response.py
gauto/libs/urllib3/util/retry.py
gauto/libs/urllib3/util/ssl_.py
gauto/libs/urllib3/util/timeout.py
gauto/libs/urllib3/util/url.py
gauto/uiautomator/__init__.py
gauto/uiautomator/accout_handler.py
gauto/uiautomator/login_getter.py
gauto/uiautomator/login_tencent.py
gauto/uiautomator/uiautomator_manager.py
gauto_android-0.1.4.dist-info/LICENSE.txt
gauto_android-0.1.4.dist-info/METADATA
gauto_android-0.1.4.dist-info/WHEEL
gauto_android-0.1.4.dist-info/top_level.txt
gauto_android-0.1.4.dist-info/RECORD
