Metadata-Version: 2.1
Name: gauto-android
Version: 0.1.4
Summary: A tool for game automation on android platform
Home-page: https://github.com/qintianchen/GAutomatorAndroid
Author: qintianchen
Author-email: 1365265750@qq.com
License: MIT Licence
Platform: UNKNOWN
Requires-Python: >=3.6
Requires-Dist: numpy (>=1.18.3)
Requires-Dist: opencv-python (>=4.2.0.34)
Requires-Dist: xlrd (>=1.2.0)
Requires-Dist: xlwt (>=1.3.0)
